Metadata-Version: 2.1
Name: msSmartHome
Version: 0.0.1
Summary: smart home package
Home-page: https://gitlab.com/michemil/mssmarthome
Author: MS
Author-email: 
License: UNKNOWN
Platform: UNKNOWN
Classifier: Programming Language :: Python :: 3
Classifier: License :: OSI Approved :: MIT License
Classifier: Operating System :: OS Independent
Requires-Python: >=3.6
